Metadata-Version: 2.1
Name: forgroundColorChanger
Version: 0.0.1
Summary: A forground color changer
Home-page: 
Author: Dean Brosnan
Author-email: deangames200@hotmail.com
License: MIT
Keywords: forgroundcolor
Classifier: Development Status :: 5 - Production/Stable
Classifier: Intended Audience :: Education
Classifier: Operating System :: Microsoft :: Windows :: Windows 11
Classifier: License :: OSI Approved :: MIT License
Classifier: Programming Language :: Python :: 3
License-File: LICENCE.txt
